br_rapp_sdk/__init__.py
br_rapp_sdk/common.py
br_rapp_sdk/a1_services/__init__.py
br_rapp_sdk/a1_services/a1_policy_types.py
br_rapp_sdk/a1_services/a1_services.py
br_rapp_sdk/a1_services/common.py
br_rapp_sdk/monitoring_services/__init__.py
br_rapp_sdk/monitoring_services/common.py
br_rapp_sdk/monitoring_services/monitoring_services.py
br_rapp_sdk/monitoring_services/monitoring_types.py
br_rapp_sdk/oam_services/__init__.py
br_rapp_sdk/oam_services/common.py
br_rapp_sdk/oam_services/network.py
br_rapp_sdk/oam_services/network_types.py
br_rapp_sdk/oam_services/oam_services.py
br_rapp_sdk/oam_services/terminal.py
br_rapp_sdk/oam_services/terminal_types.py
br_rapp_sdk-2025.12.dist-info/licenses/LICENSE
br_rapp_sdk-2025.12.dist-info/licenses/NOTICE
br_rapp_sdk-2025.12.dist-info/METADATA
br_rapp_sdk-2025.12.dist-info/WHEEL
br_rapp_sdk-2025.12.dist-info/top_level.txt
br_rapp_sdk-2025.12.dist-info/RECORD
