Metadata-Version: 2.4
Name: br_rapp_sdk
Version: 2025.12
Summary: SDK for building rApps in BubbleRAN MX-PDK
Author-email: Andrea LEONE <andrea.leone@bubbleran.com>, Ali YAGHOUBIAN <ali.yaghoubian@bubbleran.com>
Project-URL: Homepage, https://bubbleran.com/
Project-URL: Repository, https://github.com/bubbleran/rapp_sdk
Project-URL: Documentation, https://bubbleran.com/docs/devops-guide/odin/Odin/Overview
Classifier: Programming Language :: Python :: 3
Classifier: Operating System :: OS Independent
Requires-Python: >=3.12
License-File: LICENSE
License-File: NOTICE
Requires-Dist: httpx>=0.28.1
Requires-Dist: kubernetes>=32.0.1
Requires-Dist: mysql-connector-python>=8.1.0
Requires-Dist: pydantic>=2.10.6
Requires-Dist: pyyaml>=6.0.1
Requires-Dist: uvicorn>=0.37.0
Dynamic: license-file
